fhirstorm
