Metadata-Version: 1.1
Name: FHIRstorm
Version: 0.0.1.dev6
Summary: SMART on FHIR client for Python
Home-page: https://github.com/Arborian/fhirstorm
Author: Rick Copeland
Author-email: rick@arborian.com
License: Apache License Version 2.0
Platform: UNKNOWN
Classifier: Programming Language :: Python
Classifier: Programming Language :: Python :: 3.6
Classifier: Development Status :: 3 - Alpha
Classifier: License :: OSI Approved :: Apache Software License
